twip/__init__.py
twip/data_convert.py
twip/example.py
twip/models.py
twip/twip.py
twip_api-1.0.0.dist-info/LICENSE
twip_api-1.0.0.dist-info/METADATA
twip_api-1.0.0.dist-info/WHEEL
twip_api-1.0.0.dist-info/top_level.txt
twip_api-1.0.0.dist-info/RECORD
