Metadata-Version: 2.1
Name: twip-api
Version: 1.0.0
Summary: Parses the things provided by twip such as donation, follow
Home-page: https://github.com/junah201/Twip
Author: Junah201
Author-email: junah.dev@gmail.com
License: MIT
Keywords: twip,twip.kr,twitch
Classifier: Programming Language :: Python :: 3.7
Classifier: Programming Language :: Python :: 3.8
Classifier: Programming Language :: Python :: 3.9
Classifier: Programming Language :: Python :: 3.10
Requires-Python: >=3
License-File: LICENSE
Requires-Dist: websocket-client
Requires-Dist: requests
